{
  "ジャンプ系": {
    "ジャンプ・コミックス": "週刊少年ジャンプ",
    "ジャンプ コミックス": "週刊少年ジャンプ",
    "ジャンプコミックス": "週刊少年ジャンプ",
    "ヤングジャンプ・コミックス": "週刊ヤングジャンプ",
    "ヤングジャンプコミックス": "週刊ヤングジャンプ"
  },
  "サンデー系": {
    "少年サンデーコミックス": "週刊少年サンデー",
    "ヤングサンデーコミックス": "週刊ヤングサンデー",
    "裏少年サンデーコミックス": "裏サンデー",
    "サンデーGXコミックス": "月刊サンデーGX",
    "ゲッサン少年サンデーコミックススペシャル": "ゲッサン"
  },
  "マガジン系": {
    "少年マガジンコミックス": "週刊少年マガジン",
    "ヤンマガKC": "ヤングマガジン",
    "モーニングKC": "モーニング",
    "アフタヌーンKC": "アフタヌーン",
    "マガジンZ KC": "月刊マガジンZ",
    "講談社コミックスなかよし": "なかよし",
    "講談社コミックスフレンド": "フレンド",
    "講談社コミックスデザート": "デザート",
    "KCDX": "講談社各誌"
  },
  "チャンピオン系": {
    "少年チャンピオン・コミックス": "週刊少年チャンピオン",
    "ヤングチャンピオン・コミックス": "ヤングチャンピオン",
    "ヤングチャンピオンコミックス": "ヤングチャンピオン",
    "ヤングチャンピオン烈コミックス": "ヤングチャンピオン烈",
    "チャンピオンREDコミックス": "チャンピオンRED"
  },
  "集英社系（ジャンプ以外）": {
    "マーガレットコミックス": "マーガレット",
    "りぼんマスコットコミックス": "りぼん",
    "花とゆめCOMICS": "花とゆめ",
    "ヤングユーコミックス": "ヤングユー"
  },
  "小学館系（サンデー以外）": {
    "フラワーコミックス": "少女コミック",
    "ビッグコミックス": "ビッグコミック"
  },
  "角川系": {
    "角川コミックス・エース": "月刊少年エース"
  },
  "スクウェア・エニックス系": {
    "ガンガンコミックス": "月刊少年ガンガン",
    "ヤングガンガンコミックス": "ヤングガンガン",
    "ガンガンコミックスonline": "ガンガンONLINE",
    "ビッグガンガンコミックス": "ビッグガンガン"
  },
  "ヤングアニマル系": {
    "ヤングアニマルコミックス": "ヤングアニマル",
    "ヤングアニマル嵐コミックス": "ヤングアニマル嵐"
  },
  "その他": {
    "Bamboo comics": "まんがライフMOMO",
    "ACTION COMICS": "月刊アクション"
  }
}